<?xml version="1.0" encoding="utf-8" ?><dwsync><file name="wp-cron.php" server="ftp.lassena.dk/meyer/" local="3486103290" remote="3486060000" Dst="-1" /><file name="wp-activate.php" server="ftp.lassena.dk/meyer/" local="3654098323" remote="3627500400" Dst="-1" /><file name="index.php" server="ftp.lassena.dk/meyer/" local="3486103398" remote="3654132960" Dst="-1" /><file name="wp-blog-header.php" server="ftp.lassena.dk/meyer/" local="3486103384" remote="3654214980" Dst="-1" /><file name="readme.html" server="ftp.lassena.dk/meyer/" local="3594894088" remote="3594841200" Dst="-1" /><file name="wp-trackback.php" server="ftp.lassena.dk/meyer/" local="3486103278" remote="3654222780" Dst="-1" /><file name="wp-config.php" server="ftp.lassena.dk/meyer/" local="3486103398" remote="3654222780" Dst="-1" /><file name="xmlrpc.php" server="ftp.lassena.dk/meyer/" local="3486103278" remote="3654222840" Dst="-1" /><file name="wp-links-opml.php" server="ftp.lassena.dk/meyer/" local="3486103278" remote="3654222840" Dst="-1" /><file name=".gitignore" server="ftp.lassena.dk/meyer/" local="3654228970" remote="3654222840" Dst="-1" /><file name="wp-mail.php" server="ftp.lassena.dk/meyer/" local="3567028452" remote="3654222840" Dst="-1" /><file name="wp-load.php" server="ftp.lassena.dk/meyer/" local="3486103278" remote="3654222840" Dst="-1" /><file name="wp-settings.php" server="ftp.lassena.dk/meyer/" local="3486103278" remote="3654222840" Dst="-1" /><file name="wp-comments-post.php" server="ftp.lassena.dk/meyer/" local="3486103384" remote="3654222840" Dst="-1" /></dwsync>